{
    "type": "object",
    "properties": {
        "access_key": {
            "required": true,
            "type": "string"
        },
        "tonce": {
            "required": true,
            "type": "integer"
        },
        "signature": {
            "required": true,
            "type": "string"
        },
        "market": {
            "required": true,
            "type": "string"
        },
        "state": {
            "required": false,
            "type": "string"
        },
        "limit": {
            "required": false,
            "type": "integer"
        },
        "page": {
            "required": false,
            "type": "integer"
        },
        "order_by": {
            "required": false,
            "type": "string"
        }
    }
}